kids/__init__.py
kids/cache/__init__.py
kids.cache-0.0.7.dist-info/DESCRIPTION.rst
kids.cache-0.0.7.dist-info/LICENSE.txt
kids.cache-0.0.7.dist-info/METADATA
kids.cache-0.0.7.dist-info/RECORD
kids.cache-0.0.7.dist-info/WHEEL
kids.cache-0.0.7.dist-info/metadata.json
kids.cache-0.0.7.dist-info/top_level.txt
